vortex/DataWrapTuple.py
vortex/DeferUtil.py
vortex/Jsonable.py
vortex/Payload.py
vortex/PayloadEndpoint.py
vortex/PayloadEndpointTest.py
vortex/PayloadEnvelope.py
vortex/PayloadFilterKeys.py
vortex/PayloadIO.py
vortex/PayloadPriority.py
vortex/PayloadResponse.py
vortex/PayloadResponseTest.py
vortex/PayloadTest.py
vortex/PerformTestActionTuple.py
vortex/SerialiseUtil.py
vortex/TestTuple.py
vortex/Tuple.py
vortex/TupleAction.py
vortex/TupleActionVortex.py
vortex/TupleDataForTest.py
vortex/TuplePerfTest.py
vortex/TuplePolymorphicTupleTypeFieldArgTest.py
vortex/TupleRestfulTest.py
vortex/TupleSelector.py
vortex/TupleTest.py
vortex/VortexABC.py
vortex/VortexClientHttp.py
vortex/VortexClientHttpTest.py
vortex/VortexClientTcp.py
vortex/VortexClientWebsocketFactory.py
vortex/VortexConnectionABC.py
vortex/VortexFactory.py
vortex/VortexPayloadProtocol.py
vortex/VortexServer.py
vortex/VortexServerConnection.py
vortex/VortexServerHttpResource.py
vortex/VortexServerTcp.py
vortex/VortexServerWebsocket.py
vortex/VortexTcpMemoryLeakPayloadTest.py
vortex/VortexTcpMemoryLeakRawTest.py
vortex/VortexTest.py
vortex/VortexUtil.py
vortex/VortexWritePushProducer.py
vortex/__init__.py
vortex/data_loader/TupleDataLiveLockManager.py
vortex/data_loader/TupleDataLoader.py
vortex/data_loader/TupleDataLoaderDelegate.py
vortex/data_loader/TupleDataLoaderTupleABC.py
vortex/data_loader/TupleDataLoaderTuples.py
vortex/data_loader/__init__.py
vortex/event_bus/TupleChangeEventABC.py
vortex/event_bus/TupleChangeEventBus.py
vortex/event_bus/TupleChangeEventBusObserverABC.py
vortex/event_bus/__init__.py
vortex/handler/TupleActionProcessor.py
vortex/handler/TupleActionProcessorProxy.py
vortex/handler/TupleActionProcessorTestHandler.py
vortex/handler/TupleDataActionClient.py
vortex/handler/TupleDataObservableCache.py
vortex/handler/TupleDataObservableHandler.py
vortex/handler/TupleDataObservableProxyHandler.py
vortex/handler/TupleDataObservableTestHandler.py
vortex/handler/TupleDataObserverClient.py
vortexpy-4.0.23.dist-info/LICENSE
vortexpy-4.0.23.dist-info/METADATA
vortexpy-4.0.23.dist-info/WHEEL
vortexpy-4.0.23.dist-info/top_level.txt
vortexpy-4.0.23.dist-info/RECORD
