Metadata-Version: 2.2
Name: vortexpy
Version: 4.0.23
Summary: Synertys observable, routable, data serialisation and transport code.
Author-email: Synerty <contact@synerty.com>
License: MIT License
Project-URL: Homepage, https://github.com/Synerty/vortexpy
Project-URL: Download, https://github.com/Synerty/vortexpy/tarball/3.4.6
Keywords: vortex,observable,http,compressed,synerty
Classifier: Programming Language :: Python :: 3.5
License-File: LICENSE
Requires-Dist: SQLAlchemy>=2.0
Requires-Dist: GeoAlchemy2
Requires-Dist: txwebsocket>=1.1.0
Requires-Dist: autobahn[twisted]
Requires-Dist: vcversioner
Requires-Dist: six
Requires-Dist: pytz
Requires-Dist: reactivex>=4.0.4
Requires-Dist: ddt>=1.6.0
Requires-Dist: psutil
Requires-Dist: txhttputil>=1.2.0
